MANIFEST.in
README.md
setup.py
pivotal2pdf/__init__.py
pivotal2pdf/pdf.py
pivotal2pdf/util.py
pivotal2pdf.egg-info/PKG-INFO
pivotal2pdf.egg-info/SOURCES.txt
pivotal2pdf.egg-info/dependency_links.txt
pivotal2pdf.egg-info/entry_points.txt
pivotal2pdf.egg-info/requires.txt
pivotal2pdf.egg-info/top_level.txt
pivotal2pdf/icons/bug.png
pivotal2pdf/icons/chore.png
pivotal2pdf/icons/feature.png
pivotal2pdf/icons/release.png
pivotal2pdf/icons/spike.png