Metadata-Version: 1.2
Name: pivotal2pdf
Version: 1.0
Summary: A utility to generate PDFs from CSV exported from Pivotal
Home-page: https://github.com/csk-ableton/pivotal2pdf
Author: Christopher Strack
Author-email: csk@ableton.com
License: UNKNOWN
Platform: UNKNOWN
Classifier: License :: OSI Approved :: MIT License
Classifier: Intended Audience :: End Users/Desktop
Classifier: Development Status :: 5 - Production/Stable
Requires-Python: >=2.7
